README.md
setup.cfg
setup.py
aio4.egg-info/PKG-INFO
aio4.egg-info/SOURCES.txt
aio4.egg-info/dependency_links.txt
aio4.egg-info/requires.txt
aio4.egg-info/top_level.txt
scrapper_boilerplate/__init__.py
scrapper_boilerplate/account/__init__.py
scrapper_boilerplate/build/__init__.py
scrapper_boilerplate/cookies/__init__.py
scrapper_boilerplate/datababase_state/__init__.py
scrapper_boilerplate/file_handler/__init__.py
scrapper_boilerplate/output/__init__.py
scrapper_boilerplate/parser_handler/__init__.py
scrapper_boilerplate/proxy/__init__.py
scrapper_boilerplate/setup/__init__.py
scrapper_boilerplate/telegram/__init__.py
scrapper_boilerplate/timer/__init__.py
scrapper_boilerplate/warnings/__init__.py
scrapper_boilerplate/webdriver_handler/__init__.py