Metadata-Version: 2.1
Name: aio4
Version: 0.2.9
Summary: Scrapping/Automating tools, userSwitching, anti-bot detection and more...
Home-page: https://job-hunting.readthedocs.io/
Author: Jeferson/MxJeff
Author-email: mx.jeferson.10@hotmail.com
Classifier: Intended Audience :: Developers
Classifier: License :: OSI Approved :: MIT License
Classifier: Programming Language :: Python
Classifier: Programming Language :: Python :: 3
Classifier: Programming Language :: Python :: 3.6
Classifier: Programming Language :: Python :: 3.7
Classifier: Programming Language :: Python :: 3.8
Classifier: Programming Language :: Python :: 3.9
Classifier: Operating System :: OS Independent
